django_js_reverse/__init__.py
django_js_reverse/core.py
django_js_reverse/js_reverse_settings.py
django_js_reverse/models.py
django_js_reverse/rjsmin.py
django_js_reverse/views.py
django_js_reverse/management/__init__.py
django_js_reverse/management/commands/__init__.py
django_js_reverse/management/commands/collectstatic_js_reverse.py
django_js_reverse/templates/django_js_reverse/urls_js.tpl
django_js_reverse/templatetags/__init__.py
django_js_reverse/templatetags/js_reverse.py
django_js_reverse/tests/__init__.py
django_js_reverse/tests/helper.py
django_js_reverse/tests/settings.py
django_js_reverse/tests/test_urlconf_urls.py
django_js_reverse/tests/test_urls.py
django_js_reverse/tests/unit_tests.py
django_js_reverse/tests/utils.py
django_js_reverse-0.10.2.dist-info/AUTHORS
django_js_reverse-0.10.2.dist-info/LICENSE
django_js_reverse-0.10.2.dist-info/METADATA
django_js_reverse-0.10.2.dist-info/WHEEL
django_js_reverse-0.10.2.dist-info/top_level.txt
django_js_reverse-0.10.2.dist-info/RECORD
