Metadata-Version: 2.1
Name: django-js-reverse
Version: 0.10.2
Summary: Javascript url handling for Django that doesn't hurt.
Home-page: https://github.com/ierror/django-js-reverse
Download-URL: http://pypi.python.org/pypi/django-js-reverse/
Author: Bernhard Janetzki
Author-email: boerni@gmail.com
License: MIT
Classifier: Programming Language :: Python
Classifier: Programming Language :: Python :: 3
Classifier: Programming Language :: Python :: Implementation :: PyPy
Classifier: Framework :: Django
Classifier: Development Status :: 5 - Production/Stable
Classifier: License :: OSI Approved :: MIT License
License-File: LICENSE
License-File: AUTHORS
